phagetb/base/extras/PhageTB.png
phagetb/base/extras/acc_to_id.pkl
phagetb/base/extras/hostTaxa.pkl
phagetb/base/extras/hosts_list.pkl
phagetb/base/extras/id_to_acc.pkl
phagetb/base/extras/ref_host_list.pkl
phagetb/base/extras/ref_vir_list.pkl
phagetb/base/extras/ref_virus_list.pkl
phagetb/base/pretrained/model.pkl
phagetb/blast_binaries/linux/blastn
phagetb/blast_binaries/mac/blastn
phagetb/blast_binaries/windows/blastn.exe
phagetb/blast_binaries/windows/nghttp2.dll
phagetb/python_scripts/__init__.py
phagetb/python_scripts/model.py
phagetb/python_scripts/model_bacteria.py
phagetb/python_scripts/model_phage_host_pair.py
phagetb-1.6.dist-info/LICENSE
phagetb-1.6.dist-info/METADATA
phagetb-1.6.dist-info/WHEEL
phagetb-1.6.dist-info/entry_points.txt
phagetb-1.6.dist-info/top_level.txt
phagetb-1.6.dist-info/RECORD
