Metadata-Version: 2.1
Name: phagetb
Version: 1.6
Summary: A multilevel prediction method for predicting interactions between bacteriophages and pathogenic bacterial hosts
Home-page: https://github.com/raghavagps/phagetb
Requires-Python: >=3.6
Requires-Dist: numpy
Requires-Dist: pandas
Requires-Dist: argparse
Requires-Dist: scikit-learn
Requires-Dist: Bio
